guyangpip/__init__.py
guyangpip/main.py
guyangpip-2019.9.17.post2.dist-info/LICENSE
guyangpip-2019.9.17.post2.dist-info/METADATA
guyangpip-2019.9.17.post2.dist-info/WHEEL
guyangpip-2019.9.17.post2.dist-info/top_level.txt
guyangpip-2019.9.17.post2.dist-info/RECORD
