Metadata-Version: 2.1
Name: guyangpip
Version: 2019.09.17-2
Summary: A demo for python packaging.
Home-page: https://github.com/DeliangFan/packagedemo
Author: guyang
Author-email: 316903631@qq.com
License: MIT
Keywords: demo
Platform: UNKNOWN
Classifier: Programming Language :: Python :: 3
Classifier: License :: OSI Approved :: MIT License
Classifier: Operating System :: OS Independent
Requires-Python: >=3.6
